MANIFEST.in
requirements.txt
setup.py
explain/__init__.py
explain/__main__.py
explain/dump.py
explain.egg-info/PKG-INFO
explain.egg-info/SOURCES.txt
explain.egg-info/dependency_links.txt
explain.egg-info/entry_points.txt
explain.egg-info/requires.txt
explain.egg-info/top_level.txt