Metadata-Version: 1.0
Name: explain
Version: 0.1.1
Summary: Super simple create table statement dumping.
Home-page: https://github.com/Raynes/explain
Author: Anthony Grimes
Author-email: i@raynes.me
License: MIT
Platform: UNKNOWN
